baselinker/__init__.py
py_baselinker-0.0.1.dist-info/LICENSE
py_baselinker-0.0.1.dist-info/METADATA
py_baselinker-0.0.1.dist-info/WHEEL
py_baselinker-0.0.1.dist-info/top_level.txt
py_baselinker-0.0.1.dist-info/RECORD
