Metadata-Version: 2.1
Name: py-baselinker
Version: 0.0.1
Summary: Python library to communication with baselinker
Home-page: https://github.com/Solizion/py-baselinker
Author: Solizion Associations
Author-email: kontakt@solizion.pl
License: UNKNOWN
Platform: UNKNOWN
Classifier: Programming Language :: Python :: 3
Classifier: License :: OSI Approved :: Apache Software License
Classifier: Operating System :: OS Independent
Requires-Python: >=3.8
